gs_netsuite_api/__init__.py
gs_netsuite_api/_version.py
gs_netsuite_api/api.py
gs_netsuite_api/api.py.adoc
gs_netsuite_api/custom_records.py
gs_netsuite_api/data_types.py
gs_netsuite_api/ns_utils.py
gs_netsuite_api-1.4.2.dist-info/METADATA
gs_netsuite_api-1.4.2.dist-info/WHEEL
gs_netsuite_api-1.4.2.dist-info/top_level.txt
gs_netsuite_api-1.4.2.dist-info/RECORD
