Metadata-Version: 2.1
Name: gs-netsuite-api
Version: 1.4.2
Classifier: Programming Language :: Python :: 3
Classifier: Programming Language :: Python :: 3 :: Only
Requires-Python: >=3.8
Requires-Dist: netsuite
Requires-Dist: netsuite[soap_api]
Requires-Dist: zeep ==4.1
Requires-Dist: python-dotenv
